LICENSE
README.rst
setup.cfg
setup.py
hentai_chan_api/__init__.py
hentai_chan_api/content_parser.py
hentai_chan_api/data.py
hentai_chan_api/hentaichan.py
hentai_chan_api.egg-info/PKG-INFO
hentai_chan_api.egg-info/SOURCES.txt
hentai_chan_api.egg-info/dependency_links.txt
hentai_chan_api.egg-info/requires.txt
hentai_chan_api.egg-info/top_level.txt