Metadata-Version: 2.1
Name: hentai-chan-api
Version: 1.0.2
Summary: Wrapper over https://hentaichan.live | There is also an asynchronous version, go to github
Home-page: https://github.com/JKearnsl/HentaiChanApi
Author: JKearnsl
Author-email: pooolg@hotmail.com
License: MIT
Platform: UNKNOWN
Classifier: Programming Language :: Python :: 3.7
Classifier: Programming Language :: Python :: 3.8
Classifier: Programming Language :: Python :: 3.9
Classifier: Programming Language :: Python :: 3.10
Classifier: License :: OSI Approved :: MIT License
Requires-Python: >=3.7
License-File: LICENSE
